mcp_server_fetch/__init__.py
mcp_server_fetch/__main__.py
mcp_server_fetch/server.py
mcp_web_fetch_langgpt-0.6.3.dist-info/METADATA
mcp_web_fetch_langgpt-0.6.3.dist-info/WHEEL
mcp_web_fetch_langgpt-0.6.3.dist-info/entry_points.txt
mcp_web_fetch_langgpt-0.6.3.dist-info/licenses/LICENSE
mcp_web_fetch_langgpt-0.6.3.dist-info/RECORD
